{".class": "MypyFile", "_fullname": "guessTheNumber", "_name": null, "is_stub": false, "names": {".class": "SymbolTable", "__doc__": {".class": "SymbolTableNode", "kind": "Gdef", "node": {".class": "Var", "flags": [], "fullname": "guessTheNumber.__doc__", "name": "__doc__", "type": "builtins.str"}}, "__file__": {".class": "SymbolTableNode", "kind": "Gdef", "node": {".class": "Var", "flags": [], "fullname": "guessTheNumber.__file__", "name": "__file__", "type": "builtins.str"}}, "__name__": {".class": "SymbolTableNode", "kind": "Gdef", "node": {".class": "Var", "flags": [], "fullname": "guessTheNumber.__name__", "name": "__name__", "type": "builtins.str"}}, "__package__": {".class": "SymbolTableNode", "kind": "Gdef", "node": {".class": "Var", "flags": [], "fullname": "guessTheNumber.__package__", "name": "__package__", "type": "builtins.str"}}, "guess": {".class": "SymbolTableNode", "kind": "Gdef", "node": {".class": "Var", "flags": [], "fullname": "guessTheNumber.guess", "name": "guess", "type": "builtins.int"}}, "guessesTaken": {".class": "SymbolTableNode", "kind": "Gdef", "node": {".class": "Var", "flags": [], "fullname": "guessTheNumber.guessesTaken", "name": "guessesTaken", "type": "builtins.int"}}, "random": {".class": "SymbolTableNode", "cross_ref": "random", "kind": "ModuleRef"}, "secretNumber": {".class": "SymbolTableNode", "kind": "Gdef", "node": {".class": "Var", "flags": [], "fullname": "guessTheNumber.secretNumber", "name": "secretNumber", "type": "builtins.int"}}}, "path": "/home/nathias/Programs/python/inventwithpy/automatetheboring/guessTheNumber.py"}
